{"weight":0.08567136526107788,"featureIndex":2,"threshold":28.04570198059082,"left":{"weight":0.15021133422851563,"featureIndex":4,"threshold":104.1640625,"left":{"aggregate":[61.0,1.0]},"right":{"weight":0.06513446569442749,"featureIndex":5,"partition":[true,false,true,false,false,false,false,false,false,false,false,false,false,false,false,false,false,false,false,false,false,false,false,false,false,false,false,false,false,false,false],"left":{"aggregate":[34.0,26.0]},"right":{"aggregate":[20.0,3.0]}}},"right":{"weight":0.045694947242736819,"featureIndex":5,"partition":[true,false,true,false,false,false,false,false,true,false,true,false,false,false,false,true,false,true,false,true,false,true,false,true,false,false,false,false,false,false,false],"left":{"weight":0.07978177070617676,"featureIndex":0,"threshold":60.0234375,"left":{"weight":0.22816818952560426,"featureIndex":4,"threshold":85.119140625,"left":{"aggregate":[7.0,0.0]},"right":{"weight":0.09229239821434021,"featureIndex":3,"threshold":0.2838398516178131,"left":{"aggregate":[7.0,22.0]},"right":{"aggregate":[1.0,53.0]}}},"right":{"aggregate":[3.0,0.0]}},"right":{"weight":0.01835775375366211,"featureIndex":7,"threshold":0.193359375,"left":{"weight":0.015048503875732422,"featureIndex":5,"partition":[false,false,true,false,false,false,false,false,false,false,false,false,false,false,false,false,false,true,false,true,false,true,false,false,false,false,false,false,false,false,false],"left":{"aggregate":[15.0,21.0]},"right":{"aggregate":[12.0,31.0]}},"right":{"weight":0.163091242313385,"featureIndex":4,"threshold":127.095703125,"left":{"weight":0.028142213821411134,"featureIndex":4,"threshold":0.388671875,"left":{"aggregate":[0.0,2.0]},"right":{"weight":0.0528026819229126,"featureIndex":0,"threshold":25.1015625,"left":{"aggregate":[51.0,8.0]},"right":{"weight":0.07492578029632569,"featureIndex":2,"threshold":35.12265396118164,"left":{"aggregate":[19.0,20.0]},"right":{"aggregate":[27.0,7.0]}}}},"right":{"weight":0.05813974142074585,"featureIndex":4,"threshold":158.189453125,"left":{"aggregate":[20.0,36.0]},"right":{"aggregate":[5.0,38.0]}}}}}}