{"weight":0.06909751892089844,"featureIndex":2,"threshold":29.880468368530275,"left":{"weight":0.06626451015472412,"featureIndex":2,"threshold":26.2109375,"left":{"weight":0.10751157999038696,"featureIndex":5,"partition":[false,false,false,false,true,false,false,false,false,false,false,false,false,false,false,false,false,true,false,true,false,true,false,true,false,true,false,true,false,true,false],"left":{"aggregate":[46.0,1.0]},"right":{"aggregate":[34.0,13.0]}},"right":{"weight":0.0895499587059021,"featureIndex":4,"threshold":104.1640625,"left":{"aggregate":[18.0,3.0]},"right":{"aggregate":[28.0,30.0]}}},"right":{"weight":0.027170836925506593,"featureIndex":3,"threshold":0.6131836175918579,"left":{"weight":0.17222285270690919,"featureIndex":4,"threshold":127.095703125,"left":{"weight":0.10235011577606201,"featureIndex":0,"threshold":30.0234375,"left":{"weight":0.09843122959136963,"featureIndex":2,"threshold":45.34492111206055,"left":{"weight":0.054042696952819827,"featureIndex":1,"threshold":36.3515625,"left":{"aggregate":[23.0,8.0]},"right":{"aggregate":[45.0,3.0]}},"right":{"aggregate":[0.0,3.0]}},"right":{"aggregate":[27.0,30.0]}},"right":{"weight":0.07141882181167603,"featureIndex":4,"threshold":179.177734375,"left":{"weight":0.09336352348327637,"featureIndex":5,"partition":[true,false,true,false,true,false,true,false,true,false,false,false,false,false,false,true,false,true,false,true,false,false,false,true,false,true,false,false,false,true,false],"left":{"aggregate":[0.0,19.0]},"right":{"weight":0.09220385551452637,"featureIndex":6,"threshold":60.046875,"left":{"aggregate":[0.0,12.0]},"right":{"weight":0.04357588291168213,"featureIndex":3,"threshold":0.5582929849624634,"left":{"weight":0.04741561412811279,"featureIndex":4,"threshold":178.01171875,"left":{"aggregate":[21.0,42.0]},"right":{"aggregate":[2.0,0.0]}},"right":{"aggregate":[2.0,0.0]}}}},"right":{"aggregate":[0.0,23.0]}}},"right":{"weight":0.07865703105926514,"featureIndex":0,"threshold":24.046875,"left":{"aggregate":[13.0,11.0]},"right":{"weight":0.08538806438446045,"featureIndex":5,"partition":[false,false,false,false,true,false,true,false,true,false,false,false,false,false,true,false,false,false,false,true,false,false,false,false,false,false,false,false,false,true,false],"left":{"aggregate":[15.0,48.0]},"right":{"aggregate":[0.0,22.0]}}}}}